heatmiser_wifi/__init__.py
heatmiser_wifi/heatmiser_wifi.py
heatmiser_wifi-1.3.0.dist-info/LICENSE.txt
heatmiser_wifi-1.3.0.dist-info/METADATA
heatmiser_wifi-1.3.0.dist-info/WHEEL
heatmiser_wifi-1.3.0.dist-info/entry_points.txt
heatmiser_wifi-1.3.0.dist-info/top_level.txt
heatmiser_wifi-1.3.0.dist-info/RECORD
