Metadata-Version: 2.1
Name: heatmiser_wifi
Version: 1.3.0
Summary: Library for communication with Heatmiser Wifi thermostats
Home-page: http://github.com/midstar/heatmiser_wifi
Author: Joel Midstjärna
Author-email: joel.midstjarna@gmail.com
License: MIT
Project-URL: Bug Tracker, https://github.com/midstar/heatmiser_wifi/issues
Project-URL: Source Code, https://github.com/midstar/heatmiser_wifi
Keywords: heatmiser,climate,temperature,thermostat
Classifier: Development Status :: 3 - Alpha
Classifier: Intended Audience :: Developers
Classifier: Topic :: Software Development :: Build Tools
Classifier: License :: OSI Approved :: MIT License
Classifier: Programming Language :: Python :: 2.7
Classifier: Programming Language :: Python :: 3
License-File: LICENSE.txt
